{
  "round": 19,
  "global_loss": 0.9270503905486148,
  "global_accuracy": 0.8515970515970516,
  "local_performances": [
    {
      "client": 3,
      "loss": 0.3819387546857659,
      "accuracy": 0.9403973509933775
    },
    {
      "client": 4,
      "loss": 0.2521852561831474,
      "accuracy": 0.97
    },
    {
      "client": 5,
      "loss": 1.4411661837582297,
      "accuracy": 0.7769953051643192
    },
    {
      "client": 6,
      "loss": 1.1036252565394427,
      "accuracy": 0.8169790518191842
    },
    {
      "client": 7,
      "loss": 0.373601895570564,
      "accuracy": 0.96
    },
    {
      "client": 8,
      "loss": 0.8950450706481934,
      "accuracy": 0.86
    },
    {
      "client": 9,
      "loss": 0.041939166488591584,
      "accuracy": 0.98
    }
  ]
}